zcs_azzurro_api/__init__.py
zcs_azzurro_api/const.py
zcs_azzurro_api/errors.py
zcs_azzurro_api/inverter.py
zcs_azzurro_api/zcs_azzurro_inverter.py
zcs_azzurro_api/zcs_base.py
zcs_azzurro_api-2023.3.2.dist-info/LICENSE
zcs_azzurro_api-2023.3.2.dist-info/METADATA
zcs_azzurro_api-2023.3.2.dist-info/WHEEL
zcs_azzurro_api-2023.3.2.dist-info/top_level.txt
zcs_azzurro_api-2023.3.2.dist-info/RECORD
