Metadata-Version: 2.1
Name: zcs-azzurro-api
Version: 2023.3.2
Summary: Unofficial ZCS Azzurro client for Python
Home-page: https://github.com/AlePerla/zcs_azzurro_api
Author: Alessandro Perla
Author-email: sys.ale.perla@gmail.com
Classifier: Programming Language :: Python :: 3
Classifier: License :: OSI Approved :: GNU General Public License v3 (GPLv3)
Classifier: Operating System :: OS Independent
License-File: LICENSE
Requires-Dist: requests
